{
  "parent": "minecraft:recipes/root",
  "criteria": {
    "has_dye_yellow": {
      "conditions": {
        "items": [
          {
            "tag": "forge:dyes/yellow"
          }
        ]
      },
      "trigger": "minecraft:inventory_changed"
    },
    "has_the_recipe": {
      "conditions": {
        "recipe": "dcs_climate:build/black_mosaic_yellow"
      },
      "trigger": "minecraft:recipe_unlocked"
    }
  },
  "requirements": [
    [
      "has_dye_yellow",
      "has_the_recipe"
    ]
  ],
  "rewards": {
    "recipes": [
      "dcs_climate:build/black_mosaic_yellow"
    ]
  }
}