{
  "parent": "minecraft:recipes/root",
  "criteria": {
    "has_jet_lamp": {
      "conditions": {
        "items": [
          {
            "items": [
              "dcs_climate:build/chal_lamp_jet"
            ]
          }
        ]
      },
      "trigger": "minecraft:inventory_changed"
    },
    "has_the_recipe": {
      "conditions": {
        "recipe": "dcs_climate:build/chandelier_jet_0"
      },
      "trigger": "minecraft:recipe_unlocked"
    }
  },
  "requirements": [
    [
      "has_jet_lamp",
      "has_the_recipe"
    ]
  ],
  "rewards": {
    "recipes": [
      "dcs_climate:build/chandelier_jet_0"
    ]
  }
}