{
  "parent": "minecraft:recipes/root",
  "criteria": {
    "has_log_darkoak": {
      "conditions": {
        "items": [
          {
            "items": [
              "minecraft:dark_oak_log"
            ]
          }
        ]
      },
      "trigger": "minecraft:inventory_changed"
    },
    "has_the_recipe": {
      "conditions": {
        "recipe": "dcs_climate:container/cont_log_darkoak"
      },
      "trigger": "minecraft:recipe_unlocked"
    }
  },
  "requirements": [
    [
      "has_log_darkoak",
      "has_the_recipe"
    ]
  ],
  "rewards": {
    "recipes": [
      "dcs_climate:container/cont_log_darkoak"
    ]
  }
}