{
  "parent": "dcs_climate:metal/brass",
  "criteria": {
    "has_motor_t1": {
      "conditions": {
        "items": [
          {
            "tag": "dcs_climate:motors/small"
          }
        ]
      },
      "trigger": "minecraft:inventory_changed"
    }
  },
  "display": {
    "announce_to_chat": true,
    "description": {
      "translate": "advancements.dcs_climate.metal.motor_t1.desc"
    },
    "frame": "task",
    "hidden": false,
    "icon": {
      "item": "dcs_climate:machine/motor_small"
    },
    "show_toast": true,
    "title": {
      "translate": "advancements.dcs_climate.metal.motor_t1.title"
    }
  },
  "requirements": [
    [
      "has_motor_t1"
    ]
  ]
}