{
 "type": "forge:ore_shaped",
 "pattern": [
  "XXX",
  "ZYZ",
  "WWW"
 ],
 "key": {
  "X": {
   "type": "forge:ore_dict",
   "ore": "gearWood"
  },
  "Y": {
   "type": "forge:ore_dict",
   "ore": "gearBrass"
  },
  "Z": {
   "type": "forge:ore_dict",
   "ore": "plankWood"
  },
  "W": {
   "type": "forge:ore_dict",
   "ore": "ingotIron"
  }
 },
 "result": {
  "item": "dcs_climate:dcs_device_spinning_machine",
  "count": 1,
  "data": 0
 },
 "conditions": [
  {
   "type": "dcs_climate:recipe_enabled",
   "module": "machine"
  }
 ]
}