{
    "variants": {
        "powered=false,side=north":  { "model": "dcs_climate:device/dcs_device_geyser_stone", "x": 90, "uvlock": true  },
        "powered=true,side=north":  { "model": "dcs_climate:device/dcs_device_geyser_stone", "x": 90, "uvlock": true  },
        "powered=false,side=south":  { "model": "dcs_climate:device/dcs_device_geyser_stone", "x": -90, "uvlock": true  },
        "powered=true,side=south":  { "model": "dcs_climate:device/dcs_device_geyser_stone", "x": -90, "uvlock": true  },
        "powered=false,side=west":  { "model": "dcs_climate:device/dcs_device_geyser_stone", "x": 90, "y": -90,"uvlock": true  },
        "powered=true,side=west":  { "model": "dcs_climate:device/dcs_device_geyser_stone", "x": 90, "y": -90,"uvlock": true  },
        "powered=false,side=east":  { "model": "dcs_climate:device/dcs_device_geyser_stone", "x": 90, "y": 90,"uvlock": true  },
        "powered=true,side=east":  { "model": "dcs_climate:device/dcs_device_geyser_stone", "x": 90, "y": 90,"uvlock": true  },
        "powered=false,side=up":  { "model": "dcs_climate:device/dcs_device_geyser_stone" },
        "powered=true,side=up":  { "model": "dcs_climate:device/dcs_device_geyser_stone" },
        "powered=false,side=down":  { "model": "dcs_climate:device/dcs_device_geyser_stone", "x": 180, "uvlock": true },
        "powered=true,side=down":  { "model": "dcs_climate:device/dcs_device_geyser_stone", "x": 180, "uvlock": true }
    }
}