{
    "variants": {
        "side=false,type=0": { "model": "dcs_climate:build/dcs_slab_under_gypsum" },
        "side=true,type=0": { "model": "dcs_climate:build/dcs_slab_upper_gypsum" },
        "side=false,type=1": { "model": "dcs_climate:build/dcs_slab_under_glass" },
        "side=true,type=1": { "model": "dcs_climate:build/dcs_slab_upper_glass" },
        "side=false,type=2": { "model": "dcs_climate:build/dcs_slab_under_glass" },
        "side=true,type=2": { "model": "dcs_climate:build/dcs_slab_upper_glass" },
        "side=false,type=3": { "model": "dcs_climate:build/dcs_slab_under_glass" },
        "side=true,type=3": { "model": "dcs_climate:build/dcs_slab_upper_glass" },
        "side=false,type=4": { "model": "dcs_climate:build/dcs_slab_under_glass" },
        "side=true,type=4": { "model": "dcs_climate:build/dcs_slab_upper_glass" },
        "side=false,type=5": { "model": "dcs_climate:build/dcs_slab_under_glass" },
        "side=true,type=5": { "model": "dcs_climate:build/dcs_slab_upper_glass" },
        "side=false,type=6": { "model": "dcs_climate:build/dcs_slab_under_glass" },
        "side=true,type=6": { "model": "dcs_climate:build/dcs_slab_upper_glass" },
        "side=false,type=7": { "model": "dcs_climate:build/dcs_slab_under_glass" },
        "side=true,type=7": { "model": "dcs_climate:build/dcs_slab_upper_glass" }
    }
}