{
  "parent": "minecraft:recipes/root",
  "criteria": {
    "has_crop_devilsclaw": {
      "conditions": {
        "items": [
          {
            "tag": "forge:crops/devilsclaw"
          }
        ]
      },
      "trigger": "minecraft:inventory_changed"
    },
    "has_the_recipe": {
      "conditions": {
        "recipe": "dcs_climate:magic/mortar_crop_devilsclaw"
      },
      "trigger": "minecraft:recipe_unlocked"
    }
  },
  "requirements": [
    [
      "has_crop_devilsclaw",
      "has_the_recipe"
    ]
  ],
  "rewards": {
    "recipes": [
      "dcs_climate:magic/mortar_crop_devilsclaw"
    ]
  }
}