{
    "parent": "block/block",
    "ambientocclusion": true,
    "textures": {
        "particle": "blocks/planks_oak",
        "base": "blocks/planks_oak",
        "top": "blocks/planks_oak"
    },
    "elements": [
        {   "from": [ 0, 14, 0 ],
            "to": [ 16, 15.5, 16 ],
            "faces": {
                "down":  { "uv": [ 0, 0, 16, 16 ], "texture": "#base", "cullface": "down" },
                "up":    { "uv": [ 0, 0, 16, 16 ], "texture": "#base", "cullface": "up" },
                "north": { "uv": [ 0, 14, 16, 15 ], "texture": "#base", "cullface": "north" },
                "south": { "uv": [ 0, 14, 16, 15 ], "texture": "#base", "cullface": "south" },
                "west":  { "uv": [ 0, 14, 16, 15 ], "texture": "#base", "cullface": "west" },
                "east":  { "uv": [ 0, 14, 16, 15 ], "texture": "#base", "cullface": "east" }
            }
        },
        {   "from": [ 1, 15.5, 0 ],
            "to": [ 15, 16, 16 ],
            "faces": {
                "down":  { "uv": [ 1, 0, 15, 16 ], "texture": "#top", "cullface": "down" },
                "up":    { "uv": [ 1, 0, 15, 16 ], "texture": "#top", "cullface": "up" },
                "north": { "uv": [ 1, 15, 15, 16 ], "texture": "#base", "cullface": "north" },
                "south": { "uv": [ 1, 15, 15, 16 ], "texture": "#base", "cullface": "south" },
                "west":  { "uv": [ 0, 15, 16, 16 ], "texture": "#base", "cullface": "west" },
                "east":  { "uv": [ 0, 15, 16, 16 ], "texture": "#base", "cullface": "east" }
            }
        }
    ]
}

